Changelog.rst
LICENSE
MANIFEST.in
README.md
pyproject.toml
requirements.txt
setup.py
cf/#constructlist.py#
cf/__init__.py
cf/aggregate.py
cf/auxiliarycoordinate.py
cf/bounds.py
cf/cellconnectivity.py
cf/cellmeasure.py
cf/cellmethod.py
cf/cfdatetime.py
cf/cfimplementation.py
cf/classes_data_diagrams_h5_pr_new.png
cf/classes_data_diagrams_only_cfatocfdm.png
cf/classes_data_diagrams_only_dasktocfdmpr.png
cf/classes_read_write_diagrams_h5_pr_new.png
cf/classes_regrid_dir_only_largeregrid.png
cf/constants.py
cf/constructlist.py
cf/constructs.py
cf/coordinateconversion.py
cf/coordinatereference.py
cf/count.py
cf/datum.py
cf/decorators.py
cf/dimensioncoordinate.py
cf/domain.py
cf/domainancillary.py
cf/domainaxis.py
cf/domainlist.py
cf/domaintopology.py
cf/examplefield.py
cf/field.py
cf/fieldancillary.py
cf/fieldlist.py
cf/flags.py
cf/formula_terms.py
cf/functions.py
cf/index.py
cf/interiorring.py
cf/interpolationparameter.py
cf/list.py
cf/maths.py
cf/mixin_container.py
cf/nodecountproperties.py
cf/packages_data_diagrams_h5_pr_new.png
cf/packages_data_diagrams_only_cfatocfdm.png
cf/packages_data_diagrams_only_dasktocfdmpr.png
cf/packages_read_write_diagrams_h5_pr_new.png
cf/packages_regrid_dir_only_largeregrid.png
cf/partnodecountproperties.py
cf/quantization.py
cf/query.py
cf/subspacefield.py
cf/test_file.cfa
cf/tiepointindex.py
cf/timeduration.py
cf/units.py
cf/weights.py
cf/.ruff_cache/.gitignore
cf/.ruff_cache/CACHEDIR.TAG
cf/.ruff_cache/0.9.7/15860460240991020673
cf/.ruff_cache/0.9.7/3256713840513852730
cf/abstract/__init__.py
cf/data/#data.py#
cf/data/__init__.py
cf/data/creation.py
cf/data/dask_regrid.py
cf/data/dask_utils.py
cf/data/data.py
cf/data/utils.py
cf/data/array/__init__.py
cf/data/array/aggregatedarray.py
cf/data/array/boundsfromnodesarray.py
cf/data/array/cellconnectivityarray.py
cf/data/array/fullarray.py
cf/data/array/gatheredarray.py
cf/data/array/h5netcdfarray.py
cf/data/array/netcdf4array.py
cf/data/array/netcdfarray.py
cf_python.egg-info/PKG-INFO
cf_python.egg-info/SOURCES.txt
cf_python.egg-info/dependency_links.txt
cf_python.egg-info/requires.txt
cf_python.egg-info/top_level.txt
