Metadata-Version: 2.1
Name: cf-python
Version: 3.19.0
Summary: A CF-compliant earth science data analysis library
Home-page: https://ncas-cms.github.io/cf-python
Author: David Hassell
Author-email: david.hassell@ncas.ac.uk
Maintainer: David Hassell, Sadie Bartholomew
Maintainer-email: david.hassell@ncas.ac.uk, sadie.bartholomew@ncas.ac.uk
License: MIT
Keywords: cf,netcdf,UM,data,science,oceanography,meteorology,climate
Platform: Linux
Platform: MacOS
Classifier: Development Status :: 5 - Production/Stable
Classifier: Intended Audience :: Science/Research
Classifier: License :: OSI Approved :: MIT License
Classifier: Topic :: Scientific/Engineering :: Mathematics
Classifier: Topic :: Scientific/Engineering :: Physics
Classifier: Topic :: Scientific/Engineering :: Atmospheric Science
Classifier: Topic :: Utilities
Classifier: Operating System :: POSIX :: Linux
Classifier: Operating System :: MacOS
Classifier: Programming Language :: Python :: 3
Classifier: Programming Language :: Python :: 3 :: Only
Classifier: Programming Language :: Python :: 3.10
Classifier: Programming Language :: Python :: 3.11
Classifier: Programming Language :: Python :: 3.12
Classifier: Programming Language :: Python :: 3.13
Requires-Python: >=3.9
License-File: LICENSE
Requires-Dist: netCDF4==1.7.2
Requires-Dist: cftime>=1.6.4
Requires-Dist: numpy>=2.0.0
Requires-Dist: cfdm<1.13.1.0,>=1.13.0.0
Requires-Dist: psutil>=0.6.0
Requires-Dist: cfunits>=3.3.7
Requires-Dist: dask>=2025.5.1
Requires-Dist: distributed>=2025.5.1
Requires-Dist: packaging>=20.0
Requires-Dist: scipy>=1.10.0
Provides-Extra: required-c-libraries
Requires-Dist: udunits2==2.2.25; extra == "required-c-libraries"
Provides-Extra: regridding
Requires-Dist: esmpy; extra == "regridding"
Requires-Dist: ESMF>=8.0; extra == "regridding"
Provides-Extra: convolution-filters-derivatives-relative-vorticity
Requires-Dist: scipy>=1.1.0; extra == "convolution-filters-derivatives-relative-vorticity"
Provides-Extra: subspacing-with-multi-dimensional-construct-cells
Requires-Dist: matplotlib>=3.0.0; extra == "subspacing-with-multi-dimensional-construct-cells"
Provides-Extra: documentation
Requires-Dist: sphinx>=7.0.0; extra == "documentation"
Requires-Dist: sphinx-copybutton; extra == "documentation"
Requires-Dist: sphinx-toggleprompt; extra == "documentation"
Requires-Dist: sphinxcontrib-spelling; extra == "documentation"
Provides-Extra: pre-commit-hooks
Requires-Dist: pre-commit; extra == "pre-commit-hooks"
Requires-Dist: black; extra == "pre-commit-hooks"
Requires-Dist: docformatter; extra == "pre-commit-hooks"
Requires-Dist: flake8; extra == "pre-commit-hooks"
Provides-Extra: zarr
Requires-Dist: zarr>=3.1.3; extra == "zarr"
